<annotation>
    <folder>Images</folder>
    <filename>140353cb-f0cb-4096-800e-d9b4d80ae194.jpg</filename>
    <path>Images/140353cb-f0cb-4096-800e-d9b4d80ae194.jpg</path>
    <source>
        <database>Unknown</database>
    </source>
    <size>
        <width>1536</width>
        <height>1536</height>
        <depth>3</depth>
    </size>
    <segmented>0</segmented>
    <object>
        <name>pine</name>
	<damage>other</damage>
        <pose>Unspecified</pose>
        <truncated>0</truncated>
        <difficult>0</difficult>
        <bndbox>
            <xmin>1321</xmin>
            <ymin>912</ymin>
            <xmax>1451</xmax>
            <ymax>1064</ymax>
        </bndbox>
    </object>
    <object>
        <name>pine</name>
	<damage>other</damage>
        <pose>Unspecified</pose>
        <truncated>0</truncated>
        <difficult>0</difficult>
        <bndbox>
            <xmin>822</xmin>
            <ymin>253</ymin>
            <xmax>959</xmax>
            <ymax>390</ymax>
        </bndbox>
    </object>
    <object>
        <name>pine</name>
	<damage>other</damage>
        <pose>Unspecified</pose>
        <truncated>0</truncated>
        <difficult>0</difficult>
        <bndbox>
            <xmin>716</xmin>
            <ymin>185</ymin>
            <xmax>829</xmax>
            <ymax>286</ymax>
        </bndbox>
    </object>
    <object>
        <name>pine</name>
	<damage>other</damage>
        <pose>Unspecified</pose>
        <truncated>0</truncated>
        <difficult>0</difficult>
        <bndbox>
            <xmin>1166</xmin>
            <ymin>6</ymin>
            <xmax>1356</xmax>
            <ymax>168</ymax>
        </bndbox>
    </object>
    <object>
        <name>pine</name>
	<damage>other</damage>
        <pose>Unspecified</pose>
        <truncated>0</truncated>
        <difficult>0</difficult>
        <bndbox>
            <xmin>710</xmin>
            <ymin>268</ymin>
            <xmax>865</xmax>
            <ymax>438</ymax>
        </bndbox>
    </object>
    <object>
        <name>pine</name>
	<damage>other</damage>
        <pose>Unspecified</pose>
        <truncated>0</truncated>
        <difficult>0</difficult>
        <bndbox>
            <xmin>709</xmin>
            <ymin>45</ymin>
            <xmax>826</xmax>
            <ymax>148</ymax>
        </bndbox>
    </object>
    <object>
        <name>pine</name>
	<damage>other</damage>
        <pose>Unspecified</pose>
        <truncated>0</truncated>
        <difficult>0</difficult>
        <bndbox>
            <xmin>1266</xmin>
            <ymin>334</ymin>
            <xmax>1428</xmax>
            <ymax>466</ymax>
        </bndbox>
    </object>
    <object>
        <name>pine</name>
	<damage>other</damage>
        <pose>Unspecified</pose>
        <truncated>0</truncated>
        <difficult>0</difficult>
        <bndbox>
            <xmin>741</xmin>
            <ymin>402</ymin>
            <xmax>880</xmax>
            <ymax>560</ymax>
        </bndbox>
    </object>
    </annotation>