<annotation>
    <folder>Images</folder>
    <filename>f3111174-5f30-4897-8247-391efc6d8af5.jpg</filename>
    <path>Images/f3111174-5f30-4897-8247-391efc6d8af5.jpg</path>
    <source>
        <database>Unknown</database>
    </source>
    <size>
        <width>1536</width>
        <height>1536</height>
        <depth>3</depth>
    </size>
    <segmented>0</segmented>
    <object>
        <name>pine</name>
	<damage>other</damage>
        <pose>Unspecified</pose>
        <truncated>0</truncated>
        <difficult>0</difficult>
        <bndbox>
            <xmin>16</xmin>
            <ymin>450</ymin>
            <xmax>193</xmax>
            <ymax>687</ymax>
        </bndbox>
    </object>
    <object>
        <name>pine</name>
	<damage>other</damage>
        <pose>Unspecified</pose>
        <truncated>0</truncated>
        <difficult>0</difficult>
        <bndbox>
            <xmin>192</xmin>
            <ymin>308</ymin>
            <xmax>484</xmax>
            <ymax>652</ymax>
        </bndbox>
    </object>
    <object>
        <name>pine</name>
	<damage>other</damage>
        <pose>Unspecified</pose>
        <truncated>0</truncated>
        <difficult>0</difficult>
        <bndbox>
            <xmin>486</xmin>
            <ymin>273</ymin>
            <xmax>665</xmax>
            <ymax>519</ymax>
        </bndbox>
    </object>
    <object>
        <name>pine</name>
	<damage>other</damage>
        <pose>Unspecified</pose>
        <truncated>0</truncated>
        <difficult>0</difficult>
        <bndbox>
            <xmin>681</xmin>
            <ymin>244</ymin>
            <xmax>863</xmax>
            <ymax>592</ymax>
        </bndbox>
    </object>
    <object>
        <name>pine</name>
	<damage>other</damage>
        <pose>Unspecified</pose>
        <truncated>0</truncated>
        <difficult>0</difficult>
        <bndbox>
            <xmin>334</xmin>
            <ymin>464</ymin>
            <xmax>515</xmax>
            <ymax>726</ymax>
        </bndbox>
    </object>
    <object>
        <name>pine</name>
	<damage>other</damage>
        <pose>Unspecified</pose>
        <truncated>0</truncated>
        <difficult>0</difficult>
        <bndbox>
            <xmin>722</xmin>
            <ymin>27</ymin>
            <xmax>896</xmax>
            <ymax>255</ymax>
        </bndbox>
    </object>
    <object>
        <name>pine</name>
	<damage>other</damage>
        <pose>Unspecified</pose>
        <truncated>0</truncated>
        <difficult>0</difficult>
        <bndbox>
            <xmin>444</xmin>
            <ymin>0</ymin>
            <xmax>581</xmax>
            <ymax>298</ymax>
        </bndbox>
    </object>
    <object>
        <name>pine</name>
	<damage>other</damage>
        <pose>Unspecified</pose>
        <truncated>0</truncated>
        <difficult>0</difficult>
        <bndbox>
            <xmin>91</xmin>
            <ymin>52</ymin>
            <xmax>232</xmax>
            <ymax>234</ymax>
        </bndbox>
    </object>
    <object>
        <name>pine</name>
	<damage>other</damage>
        <pose>Unspecified</pose>
        <truncated>0</truncated>
        <difficult>0</difficult>
        <bndbox>
            <xmin>193</xmin>
            <ymin>179</ymin>
            <xmax>420</xmax>
            <ymax>353</ymax>
        </bndbox>
    </object>
    <object>
        <name>pine</name>
	<damage>other</damage>
        <pose>Unspecified</pose>
        <truncated>0</truncated>
        <difficult>0</difficult>
        <bndbox>
            <xmin>503</xmin>
            <ymin>492</ymin>
            <xmax>653</xmax>
            <ymax>744</ymax>
        </bndbox>
    </object>
    <object>
        <name>pine</name>
	<damage>other</damage>
        <pose>Unspecified</pose>
        <truncated>0</truncated>
        <difficult>0</difficult>
        <bndbox>
            <xmin>434</xmin>
            <ymin>1042</ymin>
            <xmax>544</xmax>
            <ymax>1226</ymax>
        </bndbox>
    </object>
    <object>
        <name>pine</name>
	<damage>other</damage>
        <pose>Unspecified</pose>
        <truncated>0</truncated>
        <difficult>0</difficult>
        <bndbox>
            <xmin>722</xmin>
            <ymin>561</ymin>
            <xmax>935</xmax>
            <ymax>755</ymax>
        </bndbox>
    </object>
    <object>
        <name>pine</name>
	<damage>other</damage>
        <pose>Unspecified</pose>
        <truncated>0</truncated>
        <difficult>0</difficult>
        <bndbox>
            <xmin>570</xmin>
            <ymin>835</ymin>
            <xmax>708</xmax>
            <ymax>1010</ymax>
        </bndbox>
    </object>
    <object>
        <name>pine</name>
	<damage>other</damage>
        <pose>Unspecified</pose>
        <truncated>0</truncated>
        <difficult>0</difficult>
        <bndbox>
            <xmin>30</xmin>
            <ymin>179</ymin>
            <xmax>237</xmax>
            <ymax>623</ymax>
        </bndbox>
    </object>
    <object>
        <name>pine</name>
	<damage>other</damage>
        <pose>Unspecified</pose>
        <truncated>0</truncated>
        <difficult>0</difficult>
        <bndbox>
            <xmin>226</xmin>
            <ymin>0</ymin>
            <xmax>405</xmax>
            <ymax>242</ymax>
        </bndbox>
    </object>
    </annotation>